trevorspray/__init__.py
trevorspray/cli.py
trevorspray/lib/discover.py
trevorspray/lib/enumerators/__init__.py
trevorspray/lib/enumerators/base.py
trevorspray/lib/enumerators/onedrive.py
trevorspray/lib/enumerators/seamless_sso.py
trevorspray/lib/enumerators/teams_photo.py
trevorspray/lib/errors.py
trevorspray/lib/logger.py
trevorspray/lib/looters/base.py
trevorspray/lib/looters/msol.py
trevorspray/lib/proxy.py
trevorspray/lib/sprayers/__init__.py
trevorspray/lib/sprayers/adfs.py
trevorspray/lib/sprayers/anyconnect.py
trevorspray/lib/sprayers/auth0.py
trevorspray/lib/sprayers/base.py
trevorspray/lib/sprayers/jumpcloud.py
trevorspray/lib/sprayers/msol.py
trevorspray/lib/sprayers/officehome.py
trevorspray/lib/sprayers/okta.py
trevorspray/lib/sprayers/owa.py
trevorspray/lib/trevor.py
trevorspray/lib/util/__init__.py
trevorspray/lib/util/misc.py
trevorspray/lib/util/ntlmdecoder.py
trevorspray/lib/util/threadpool.py
trevorspray-2.4.0.dist-info/METADATA
trevorspray-2.4.0.dist-info/WHEEL
trevorspray-2.4.0.dist-info/entry_points.txt
trevorspray-2.4.0.dist-info/licenses/LICENSE
trevorspray-2.4.0.dist-info/RECORD
