Metadata-Version: 2.4
Name: trevorspray
Version: 2.4.0
Summary: A modular password sprayer with threading, SSH proxying, loot modules, and more
License: GPL-3.0
License-File: LICENSE
Author: TheTechromancer
Requires-Python: >=3.9,<4.0
Classifier: License :: OSI Approved :: GNU General Public License v3 (GPLv3)
Classifier: Programming Language :: Python :: 3
Classifier: Programming Language :: Python :: 3.9
Classifier: Programming Language :: Python :: 3.10
Classifier: Programming Language :: Python :: 3.11
Classifier: Programming Language :: Python :: 3.12
Classifier: Programming Language :: Python :: 3.13
Classifier: Programming Language :: Python :: 3.14
Requires-Dist: beautifulsoup4 (>=4.12.3,<5.0.0)
Requires-Dist: exchangelib (>=5.5.0,<6.0.0)
Requires-Dist: mechanicalsoup (>=1.3.0,<2.0.0)
Requires-Dist: pygments (>=2.19.1,<3.0.0)
Requires-Dist: pysocks (>=1.7.1,<2.0.0)
Requires-Dist: sh (>=2.2.1,<3.0.0)
Requires-Dist: tldextract (>=5.1.3,<6.0.0)
Requires-Dist: trevorproxy (>=1.0.8,<2.0.0)
Project-URL: Homepage, https://github.com/blacklanternsecurity/TREVORspray
Project-URL: Repository, https://github.com/blacklanternsecurity/TREVORspray
